LICENSE
MANIFEST.in
README.md
letexpr.py
setup.py
letexpr.egg-info/PKG-INFO
letexpr.egg-info/SOURCES.txt
letexpr.egg-info/dependency_links.txt
letexpr.egg-info/top_level.txt