Metadata-Version: 1.1
Name: letexpr
Version: 0.3.1
Summary: imitation of let expression like a Haskell.
Home-page: https://github.com/hachibeeDI/letexpr
Author: OGURA_Daiki
Author-email: 8hachibee125@gmail.com
License: The MIT License (MIT)
